nameguard/__init__.py
nameguard/checks/__init__.py
nameguard/checks/dna/__init__.py
nameguard/checks/dna/normalized.py
nameguard/checks/dna/punycode.py
nameguard/checks/grapheme/__init__.py
nameguard/checks/grapheme/confusables.py
nameguard/checks/grapheme/font_support.py
nameguard/checks/grapheme/invisible.py
nameguard/checks/grapheme/typing_difficulty.py
nameguard/checks/label/__init__.py
nameguard/checks/label/mixed_scripts.py
nameguard/checks/label/namewrapper.py
nameguard/checks/label/unknown.py
nameguard/checks/name/__init__.py
nameguard/checks/name/decentralized_name.py
nameguard/checks/name/impersonation_risk.py
nameguard/checks/name/namewrapper_fuses.py
nameguard/context.py
nameguard/endpoints.py
nameguard/exceptions.py
nameguard/generic_utils.py
nameguard/grapheme_normalization.py
nameguard/lambda.py
nameguard/logging.py
nameguard/models/__init__.py
nameguard/models/checks.py
nameguard/models/request.py
nameguard/models/result.py
nameguard/nameguard.py
nameguard/our_ens.py
nameguard/provider.py
nameguard/subgraph.py
nameguard/utils.py
nameguard/web_api.py
nameguard-0.1.12.dist-info/LICENSE
nameguard-0.1.12.dist-info/METADATA
nameguard-0.1.12.dist-info/WHEEL
nameguard-0.1.12.dist-info/RECORD
