Metadata-Version: 2.3
Name: nameguard
Version: 0.1.12
Summary: Security "x-ray" for ENS names
Home-page: https://nameguard.io
License: LICENSE
Author: NameHash Team
Author-email: devops@namehash.io
Maintainer: NameHash Team
Maintainer-email: devops@namehash.io
Requires-Python: >=3.9,<3.13
Classifier: License :: Other/Proprietary License
Classifier: Programming Language :: Python :: 3
Classifier: Programming Language :: Python :: 3.9
Classifier: Programming Language :: Python :: 3.10
Classifier: Programming Language :: Python :: 3.11
Classifier: Programming Language :: Python :: 3.12
Provides-Extra: lambda
Requires-Dist: aiohttp (>=3.10.11)
Requires-Dist: ens-label-inspector (>=0.2.14,<0.3.0)
Requires-Dist: eth-typing (>=4.4.0,<5.0.0)
Requires-Dist: fastapi (>=0.115.4,<0.116.0)
Requires-Dist: hexbytes (>=0.3.1,<0.4.0)
Requires-Dist: httpx (>=0.25.0,<0.26.0)
Requires-Dist: mangum (>=0.17.0,<0.18.0) ; extra == "lambda"
Requires-Dist: python-dotenv (>=1.0.0,<2.0.0)
Requires-Dist: web3 (==6.11.1)
Project-URL: Repository, https://github.com/namehash/namekit
